pythread/__init__.py
pythread/pythread.py
pythread-1.5.0.dist-info/LICENSE
pythread-1.5.0.dist-info/METADATA
pythread-1.5.0.dist-info/WHEEL
pythread-1.5.0.dist-info/top_level.txt
pythread-1.5.0.dist-info/RECORD
