Metadata-Version: 2.1
Name: pythread
Version: 1.5.0
Summary: A Python library providing a user-friendly interface for managing both synchronous and asynchronous threads.
Home-page: https://github.com/DedInc/pythread
Author: Maehdakvan
Author-email: visitanimation@google.com
Project-URL: Bug Tracker, https://github.com/DedInc/pythread/issues
Classifier: Programming Language :: Python :: 3
Classifier: License :: OSI Approved :: MIT License
Classifier: Operating System :: OS Independent
Requires-Python: >=3.0
License-File: LICENSE
Requires-Dist: asyncio
